CHANGELOG.md
big_slpp/__init__.py
big_slpp/utils.py
big_slpp-1.0.5.dist-info/LICENSE
big_slpp-1.0.5.dist-info/WHEEL
big_slpp-1.0.5.dist-info/METADATA
big_slpp-1.0.5.dist-info/RECORD
