Metadata-Version: 2.1
Name: big-slpp
Version: 1.0.5
Summary: SirAnthony's SLPP, but modernized code (also, trailing comma's)
Home-page: https://github.com/NostraDavid/big-slpp
License: MIT
Author: NostraDavid
Author-email: 55331731+nostradavid@users.noreply.github.com
Requires-Python: >=3.9,<4.0
Classifier: License :: OSI Approved :: MIT License
Classifier: Programming Language :: Python :: 3
Classifier: Programming Language :: Python :: 3.10
Classifier: Programming Language :: Python :: 3.9
Project-URL: Repository, https://github.com/NostraDavid/big-slpp
